combinadics/__init__.py
combinadics/combinadics.py
combinadics-0.0.3.dist-info/LICENSE
combinadics-0.0.3.dist-info/METADATA
combinadics-0.0.3.dist-info/WHEEL
combinadics-0.0.3.dist-info/top_level.txt
combinadics-0.0.3.dist-info/RECORD
