Metadata-Version: 2.1
Name: combinadics
Version: 0.0.3
Summary: Combinatorial system of degree k ranking and unranking.
Home-page: https://github.com/neoglez/combinadics
Author: Yansel Gonzalez Tejeda
Author-email: neoglez@gmail.com
License: UNKNOWN
Platform: UNKNOWN
Classifier: Programming Language :: Python :: 2
Classifier: Programming Language :: Python :: 3
Classifier: License :: OSI Approved :: MIT License
Classifier: Operating System :: OS Independent
License-File: LICENSE
